ista_daslab_dense_mfac.cpython-38-x86_64-linux-gnu.so
ista_daslab_micro_adam.cpython-38-x86_64-linux-gnu.so
ista_daslab_sparse_mfac.cpython-38-x86_64-linux-gnu.so
ista_daslab_tools.cpython-38-x86_64-linux-gnu.so
ista_daslab_optimizers/__init__.py
ista_daslab_optimizers/tools.py
ista_daslab_optimizers/acdc/__init__.py
ista_daslab_optimizers/acdc/acdc.py
ista_daslab_optimizers/acdc/wd_scheduler.py
ista_daslab_optimizers/dense_mfac/__init__.py
ista_daslab_optimizers/dense_mfac/dense_core_mfac.py
ista_daslab_optimizers/dense_mfac/dense_mfac.py
ista_daslab_optimizers/ista_optimizer/__init__.py
ista_daslab_optimizers/ista_optimizer/ista_optimizer.py
ista_daslab_optimizers/micro_adam/__init__.py
ista_daslab_optimizers/micro_adam/micro_adam.py
ista_daslab_optimizers/sparse_mfac/__init__.py
ista_daslab_optimizers/sparse_mfac/sparse_core_mfac_w_ef.py
ista_daslab_optimizers/sparse_mfac/sparse_mfac.py
ista_daslab_optimizers-1.1.7.dist-info/LICENSE
ista_daslab_optimizers-1.1.7.dist-info/METADATA
ista_daslab_optimizers-1.1.7.dist-info/WHEEL
ista_daslab_optimizers-1.1.7.dist-info/top_level.txt
ista_daslab_optimizers-1.1.7.dist-info/RECORD
