Metadata-Version: 2.1
Name: ista_daslab_optimizers
Version: 1.1.7
Summary: Deep Learning optimizers developed in the Distributed Algorithms and Systems group (DASLab) @ Institute of Science and Technology Austria (ISTA)
Author-email: Ionut-Vlad Modoranu <ionut-vlad.modoranu@ist.ac.at>
Maintainer-email: Ionut-Vlad Modoranu <ionut-vlad.modoranu@ist.ac.at>
License: Apache License
Project-URL: Repository, https://github.com/IST-DASLab/ISTA-DASLab-Optimizers
Keywords: adaptive optimization,deep learning,low memory optimization
Classifier: Programming Language :: Python :: 3.8
Classifier: License :: OSI Approved :: Apache Software License
Requires-Python: >=3.8
License-File: LICENSE
Requires-Dist: torch
Requires-Dist: torchaudio
Requires-Dist: torchvision
Requires-Dist: numpy
Requires-Dist: wandb
Requires-Dist: gpustat
Requires-Dist: timm
Requires-Dist: einops
Requires-Dist: psutil
Requires-Dist: fast-hadamard-transform
